IHEWAcollect/__init__.py
IHEWAcollect/accounts-template.yml
IHEWAcollect/download.py
IHEWAcollect/base/__init__.py
IHEWAcollect/base/base.py
IHEWAcollect/base/base.yml
IHEWAcollect/base/exception.py
IHEWAcollect/base/user.py
IHEWAcollect/scripts/__init__.py
IHEWAcollect/scripts/credential.py
IHEWAcollect/scripts/main.py
IHEWAcollect/scripts/skeleton.py
IHEWAcollect/templates/__init__.py
IHEWAcollect/templates/collect.py
IHEWAcollect/templates/download_tiles_test.py
IHEWAcollect/templates/dtime.py
IHEWAcollect/templates/gis.py
IHEWAcollect/templates/util.py
IHEWAcollect/templates/EU/Copernicus.py
IHEWAcollect/templates/EU/ECMWF.py
IHEWAcollect/templates/EU/GLEAM.py
IHEWAcollect/templates/EU/JRC.py
IHEWAcollect/templates/EU/__init__.py
IHEWAcollect/templates/FAO/WaPOR.py
IHEWAcollect/templates/FAO/WaporAPI.py
IHEWAcollect/templates/FAO/__init__.py
IHEWAcollect/templates/FAO/catalog_2.pickle
IHEWAcollect/templates/HydroSHEDS/DEM.py
IHEWAcollect/templates/HydroSHEDS/__init__.py
IHEWAcollect/templates/IHE/ALEXI.py
IHEWAcollect/templates/IHE/CMRSET.py
IHEWAcollect/templates/IHE/ETmonitor.py
IHEWAcollect/templates/IHE/ETmonitor_create.py
IHEWAcollect/templates/IHE/HiHydroSoil.py
IHEWAcollect/templates/IHE/SEBS.py
IHEWAcollect/templates/IHE/TWC.py
IHEWAcollect/templates/IHE/__init__.py
IHEWAcollect/templates/ISRIC/SoilGrids.py
IHEWAcollect/templates/ISRIC/__init__.py
IHEWAcollect/templates/MSWEP/__init__.py
IHEWAcollect/templates/NASA/CSR-v3.1.html
IHEWAcollect/templates/NASA/CSR-v3.2.html
IHEWAcollect/templates/NASA/CSR.py
IHEWAcollect/templates/NASA/GFZ-v3.1.html
IHEWAcollect/templates/NASA/GFZ-v3.2.html
IHEWAcollect/templates/NASA/GFZ.py
IHEWAcollect/templates/NASA/GLDAS.py
IHEWAcollect/templates/NASA/GPM.py
IHEWAcollect/templates/NASA/JPL-v3.1.html
IHEWAcollect/templates/NASA/JPL-v3.2.html
IHEWAcollect/templates/NASA/JPL.py
IHEWAcollect/templates/NASA/PODAAC.py
IHEWAcollect/templates/NASA/TRMM.py
IHEWAcollect/templates/NASA/__init__.py
IHEWAcollect-0.0.31.dist-info/AUTHORS.rst
IHEWAcollect-0.0.31.dist-info/LICENSE.rst
IHEWAcollect-0.0.31.dist-info/METADATA
IHEWAcollect-0.0.31.dist-info/WHEEL
IHEWAcollect-0.0.31.dist-info/entry_points.txt
IHEWAcollect-0.0.31.dist-info/top_level.txt
IHEWAcollect-0.0.31.dist-info/RECORD
