Metadata-Version: 2.1
Name: IHEWAcollect
Version: 0.0.31
Summary: Water Accounting Collect Tools
Home-page: https://github.com/wateraccounting/IHEWAcollect
Author: Quan Pan
Author-email: quanpan302@hotmail.com
License: GPLv3
Project-URL: Documentation, https://ihewacollect.readthedocs.io/en/latest/
Keywords: GDAL,Water
Platform: any
Classifier: Development Status :: 4 - Beta
Classifier: Programming Language :: Python :: 3
Classifier: Programming Language :: Python :: 3.5
Classifier: Programming Language :: Python :: 3.6
Classifier: Programming Language :: Python :: 3.7
Requires-Python: >=3.5
License-File: LICENSE.rst
License-File: AUTHORS.rst
Requires-Dist: cftime (>=1.0.3)
Requires-Dist: cython (>=0.29)
Requires-Dist: psutil (>=5.6)
Requires-Dist: joblib (>=0.13)
Requires-Dist: cryptography (>=2.6)
Requires-Dist: PyYAML (>=5.1)
Requires-Dist: beautifulsoup4 (>=4.8)
Requires-Dist: requests (>=2.22)
Requires-Dist: paramiko (>=2.6)
Requires-Dist: pycurl (>=7.43)
Requires-Dist: ecmwf-api-client (>=1.5)
Requires-Dist: scipy (>=1.0)
Requires-Dist: scikit-image (>=0.15)
Requires-Dist: numpy (>=1.18)
Requires-Dist: pandas (>=0.20)
Requires-Dist: netCDF4 (>=1.5)
Requires-Dist: pyproj (>=2.0)
Provides-Extra: testing
Requires-Dist: pytest ; extra == 'testing'
Requires-Dist: pytest-cov ; extra == 'testing'
